{"1731":[],"1737":[],"1741":[],"1751":[],"1856":[],"1857":[],"1900":[{"entity_id":"28","action":"lights_turn_on","orig_sensor":"1900","transitiontime":0}],"1924":[],"1931":[],"2105":[],"2140":[],"2200":[{"value":"3","entity_id":"2","action":"activate_scene","orig_sensor":"2200","transitiontime":0}],"2304":[],"s16":{"v4002":[{"value":null,"entity_id":"2","action":"groups_turn_off","transitiontime":0,"orig_sensor":"16","orig_value":"4002"}],"v1002":[{"value":"1","entity_id":"2","action":"activate_scene","orig_sensor":"16","orig_value":"1002","transitiontime":0}],"v2002":[{"value":null,"entity_id":"2","action":"lights_toggle","transitiontime":0,"orig_sensor":"16","orig_value":"2002"}],"v3002":[{"value":null,"entity_id":"24","action":"lights_toggle","transitiontime":0,"orig_sensor":"16","orig_value":"3002"},{"value":255,"entity_id":"24","action":"lights_brightness","orig_sensor":"16","orig_value":"3002","transitiontime":0}],"v3003":[{"value":15,"entity_id":"24","action":"lights_brightness","orig_sensor":"16","orig_value":"3003","transitiontime":0},{"value":null,"entity_id":"2","action":"lights_turn_off","transitiontime":0,"orig_sensor":"16","orig_value":"3003"}]},"s5":{"v2002":[{"value":null,"entity_id":"3","action":"groups_toggle","transitiontime":0,"orig_sensor":"5","orig_value":"2002"}],"v1002":[{"value":null,"entity_id":"22","action":"lights_toggle","transitiontime":0,"orig_sensor":"5","orig_value":"1002"}],"v3002":[{"value":null,"entity_id":"12","action":"lights_toggle","transitiontime":0,"orig_sensor":"5","orig_value":"3002"}]},"s2":{"v2002":[{"value":null,"entity_id":"22","action":"lights_toggle","transitiontime":0,"orig_sensor":"2","orig_value":"2002"}],"v3002":[{"value":"1","conditions":[{"child_key":"","id":"hours","key":"","value":"20","type":"time","op":"<="}],"entity_id":"2","action":"activate_scene","orig_sensor":"2","orig_value":"3002","transitiontime":0}],"v1002":[{"entity_id":"12","action":"lights_toggle","orig_sensor":"2","orig_value":"1002","transitiontime":0}]},"s19":{"v2002":[{"value":"2","conditions":[{"child_key":"","id":"hours","key":"","value":"15","type":"time","op":">"}],"entity_id":"7","action":"activate_scene","orig_sensor":"19","orig_value":"2002","transitiontime":0},{"value":"1","conditions":[{"child_key":"","id":"hours","key":"","value":"15","type":"time","op":"<="}],"entity_id":"7","action":"activate_scene","orig_sensor":"19","orig_value":"2002","transitiontime":0}],"v1002":[{"value":null,"entity_id":"7","action":"groups_turn_off","transitiontime":0,"orig_sensor":"19","orig_value":"1002"}],"v3002":[{"value":"3","entity_id":"7","action":"activate_scene","orig_sensor":"19","orig_value":"3002","transitiontime":0}]},"s7":{"ptrue":[{"value":null,"entity_id":"12","action":"lights_turn_on","transitiontime":0,"duration":"10","conditions":[{"child_key":"lux","id":"10","key":"state","value":"20","type":"sensors","op":"<="},{"child_key":"","id":"hours","key":"state","value":"7","type":"time","op":">="}],"orig_sensor":"7","orig_value":"true"}]},"s3":{"v1002":[{"entity_id":"1","action":"groups_toggle","transitiontime":0,"orig_sensor":"3","orig_value":"1002","value":255}],"v2002":[{"entity_id":"5","action":"lights_toggle","transitiontime":0,"orig_sensor":"3","orig_value":"2002"}],"v3002":[{"entity_id":"6","action":"lights_toggle","transitiontime":0,"orig_sensor":"3","orig_value":"3002"},{"entity_id":"25","action":"lights_toggle","transitiontime":0,"orig_sensor":"3","orig_value":"3002"}]},"0000":[{"entity_id":"7","action":"groups_turn_off","transitiontime":0,"orig_sensor":"0000"},{"entity_id":"2","action":"groups_turn_off","transitiontime":0,"orig_sensor":"0000"}],"sunset":[{"value":"2","entity_id":"7","action":"activate_scene","orig_sensor":"unset","transitiontime":0}],"0101":[],"s17":{"ptrue":[{"entity_id":"11","action":"groups_turn_on","transitiontime":0,"duration":"5","orig_sensor":"17","orig_value":"true","conditions":[{"child_key":"lux","id":"10","key":"state","value":"20","type":"sensors","op":"<="}]}]},"s11":{"ptrue":[{"entity_id":"6","action":"lights_turn_on","transitiontime":0,"orig_sensor":"11","orig_value":"true","conditions":[{"child_key":"","id":"hours","key":"","value":"19","type":"time","op":">="}]},{"entity_id":"25","action":"lights_turn_on","transitiontime":0,"orig_sensor":"11","orig_value":"true","conditions":[{"child_key":"","id":"hours","key":"","value":"19","type":"time","op":">="}]}]},"0845":[{"entity_id":"13","action":"groups_turn_off","transitiontime":0,"conditions":[{"child_key":"","id":"weekday","key":"","value":"true","type":"time","op":"=="}],"orig_sensor":"0845"}],"sunrise":[{"entity_id":"28","action":"lights_turn_off","orig_sensor":"unrise","transitiontime":0}],"0104":[],"0658":[],"0632":[],"0700":[{"value":"2","entity_id":"1","action":"activate_scene","conditions":[{"child_key":"","id":"weekday","key":"state","value":"true","type":"time","op":"=="}],"orig_sensor":"0700","transitiontime":0}],"0103":[],"0105":[],"0102":[],"0107":[]}
